pycersi/__init__.py
pycersi/bot.py
pycersi/privator.py
pycersi/pycersi.py
pycersi-6.1.0.dist-info/LICENSE.txt
pycersi-6.1.0.dist-info/METADATA
pycersi-6.1.0.dist-info/WHEEL
pycersi-6.1.0.dist-info/top_level.txt
pycersi-6.1.0.dist-info/RECORD
