Metadata-Version: 2.1
Name: pycersi
Version: 6.1.0
Summary: PyCersi is a lightweight Python library for number-related utilities. It offers mathematical functions, checkers, and stack operations, simplifying common tasks. Easy to install via pip , it's designed for efficient integration into various Python projects.
Home-page: https://github.com/subhrachakraborti/PyCersi
Author: Subhra Chakraborti
Author-email: mail@subhrachakraborti.com
License: MIT
Keywords: PyCersi
Classifier: Programming Language :: Python :: 3
Classifier: License :: OSI Approved :: MIT License
Classifier: Operating System :: OS Independent
Requires-Python: >3.5
License-File: LICENSE.txt
